FPGA_Matrix_Multiplication/FPGA_Hardware Accelerator/project_3.srcs/sources_1/new/seven_seg_display.v
`timescale 1ns / 1ps
module seven_seg_display(
    input wire clk,
    input wire [7:0] val0,
    input wire [7:0] val1,
    input wire [7:0] val2,
    input wire [7:0] val3,
    output reg [3:0] an,     // Anode signals
    output reg [6:0] seg     // Cathode signals
);

    reg [1:0] refresh_counter = 0;
    reg [3:0] current_value;

    always @(posedge clk) begin
        refresh_counter <= refresh_counter + 1;
    end

    always @(*) begin
        case (refresh_counter)
            2'b00: begin
                an = 4'b1110;
                current_value = val0[3:0];
            end
            2'b01: begin
                an = 4'b1101;
                current_value = val1[3:0];
            end
            2'b10: begin
                an = 4'b1011;
                current_value = val2[3:0];
            end
            2'b11: begin
                an = 4'b0111;
                current_value = val3[3:0];
            end
            default: begin
                an = 4'b1111;
                current_value = 4'b0000;
            end
        endcase
    end

    always @(*) begin
        case(current_value)
            4'h0: seg = 7'b1000000;
            4'h1: seg = 7'b1111001;
            4'h2: seg = 7'b0100100;
            4'h3: seg = 7'b0110000;
            4'h4: seg = 7'b0011001;
            4'h5: seg = 7'b0010010;
            4'h6: seg = 7'b0000010;
            4'h7: seg = 7'b1111000;
            4'h8: seg = 7'b0000000;
            4'h9: seg = 7'b0010000;
            4'hA: seg = 7'b0001000;
            4'hB: seg = 7'b0000011;
            4'hC: seg = 7'b1000110;
            4'hD: seg = 7'b0100001;
            4'hE: seg = 7'b0000110;
            4'hF: seg = 7'b0001110;
            default: seg = 7'b1111111;
        endcase
    end

endmodule

FPGA_Matrix_Multiplication/FPGA_Hardware Accelerator/project_3.srcs/sources_1/new/normal_matrix_multiplier.v
module normal_matrix_multiplier(
    input wire clk,
    output reg [7:0] result00,
    output reg [7:0] result01,
    output reg [7:0] result10,
    output reg [7:0] result11
);

    reg [3:0] A [0:1][0:1];
    reg [3:0] B [0:1][0:1];
    reg [1:0] state = 0;

    initial begin
        A[0][0] = 4'd2; A[0][1] = 4'd3;
        A[1][0] = 4'd1; A[1][1] = 4'd4;

        B[0][0] = 4'd5; B[0][1] = 4'd6;
        B[1][0] = 4'd7; B[1][1] = 4'd8;
    end

    always @(posedge clk) begin
        case (state)
            0: result00 <= (A[0][0] * B[0][0]) + (A[0][1] * B[1][0]);
            1: result01 <= (A[0][0] * B[0][1]) + (A[0][1] * B[1][1]);
            2: result10 <= (A[1][0] * B[0][0]) + (A[1][1] * B[1][0]);
            3: result11 <= (A[1][0] * B[0][1]) + (A[1][1] * B[1][1]);
        endcase
        state <= state + 1;
    end
endmodule

FPGA_Matrix_Multiplication/FPGA_Hardware Accelerator/project_3.srcs/sources_1/new/matrix_multiplier.v
module matrix_multiplier(
    input wire clk,
    output reg [7:0] result00,
    output reg [7:0] result01,
    output reg [7:0] result10,
    output reg [7:0] result11
);

    // Define 2x2 matrices (hardcoded values )
    reg [3:0] A00 = 4'd2, A01 = 4'd3;
    reg [3:0] A10 = 4'd1, A11 = 4'd4;

    reg [3:0] B00 = 4'd5, B01 = 4'd6;
    reg [3:0] B10 = 4'd7, B11 = 4'd8;

    always @(posedge clk) begin
        result00 <= (A00 * B00) + (A01 * B10);
        result01 <= (A00 * B01) + (A01 * B11);
        result10 <= (A10 * B00) + (A11 * B10);
        result11 <= (A10 * B01) + (A11 * B11);
    end

endmodule

FPGA_Matrix_Multiplication/FPGA_Hardware Accelerator/project_3.srcs/sources_1/new/top_compare.v
module top_compare(
    input wire clk,
    input wire sel, // 0 = accelerator, 1 = normal multiplier
    output wire [6:0] seg,
    output wire [3:0] an
);

    wire [7:0] acc00, acc01, acc10, acc11;
    wire [7:0] norm00, norm01, norm10, norm11;

    matrix_multiplier acc(
        .clk(clk),
        .result00(acc00),
        .result01(acc01),
        .result10(acc10),
        .result11(acc11)
    );

    normal_matrix_multiplier norm(
        .clk(clk),
        .result00(norm00),
        .result01(norm01),
        .result10(norm10),
        .result11(norm11)
    );

    seven_seg_display display(
        .clk(clk),
        .val0(sel ? norm00 : acc00),
        .val1(sel ? norm01 : acc01),
        .val2(sel ? norm10 : acc10),
        .val3(sel ? norm11 : acc11),
        .seg(seg),
        .an(an)
    );

endmodule

FPGA_Matrix_Multiplication/FPGA_Hardware Accelerator/project_3.srcs/sim_1/new/testbench.v
module testbench();
    reg clk = 0;
    reg sel = 0;
    wire [6:0] seg;
    wire [3:0] an;

    // Instantiate the top-level comparison module
    top_compare uut (
        .clk(clk),
        .sel(sel),
        .seg(seg),
        .an(an)
    );

    // Clock: 100 MHz (10 ns period)
    always #5 clk = ~clk;

    // Separate wires to monitor internals
    wire [7:0] acc00 = uut.acc.result00;
    wire [7:0] acc01 = uut.acc.result01;
    wire [7:0] acc10 = uut.acc.result10;
    wire [7:0] acc11 = uut.acc.result11;

    wire [7:0] norm00 = uut.norm.result00;
    wire [7:0] norm01 = uut.norm.result01;
    wire [7:0] norm10 = uut.norm.result10;
    wire [7:0] norm11 = uut.norm.result11;

    initial begin
        $dumpfile("matrix_compare.vcd");
        $dumpvars(0, testbench);

        // Phase 1: Accelerator mode
        sel = 0;
        #100;  // 100ns = 10 clock cycles

        // Phase 2: Normal multiplier mode
        sel = 1;
        #100;  // Observe normal multiplier progress over next 100ns

        $finish;
    end
endmodule

FPGA_Matrix_Multiplication/FPGA_Hardware Accelerator/project_3.sim/sim_1/behav/xsim/matrix_compare.vcd
$date
   Sat May  3 16:56:22 2025
$end

$version
  2024.2.0
  $dumpfile ("matrix_compare.vcd") 
$end

$timescale
  1ps
$end

$scope module testbench $end
$var reg 1 ! clk $end
$var reg 1 " sel $end
$var wire 7 # seg [6:0] $end
$var wire 4 $ an [3:0] $end
$var wire 8 % acc00 [7:0] $end
$var wire 8 & acc01 [7:0] $end
$var wire 8 ' acc10 [7:0] $end
$var wire 8 ( acc11 [7:0] $end
$var wire 8 ) norm00 [7:0] $end
$var wire 8 * norm01 [7:0] $end
$var wire 8 + norm10 [7:0] $end
$var wire 8 , norm11 [7:0] $end
$scope module uut $end
$var wire 1 - clk $end
$var wire 1 . sel $end
$var wire 7 # seg [6:0] $end
$var wire 4 $ an [3:0] $end
$var wire 8 / acc00 [7:0] $end
$var wire 8 0 acc01 [7:0] $end
$var wire 8 1 acc10 [7:0] $end
$var wire 8 2 acc11 [7:0] $end
$var wire 8 3 norm00 [7:0] $end
$var wire 8 4 norm01 [7:0] $end
$var wire 8 5 norm10 [7:0] $end
$var wire 8 6 norm11 [7:0] $end
$scope module acc $end
$var wire 1 - clk $end
$var reg 8 7 result00 [7:0] $end
$var reg 8 8 result01 [7:0] $end
$var reg 8 9 result10 [7:0] $end
$var reg 8 : result11 [7:0] $end
$var reg 4 ; A00 [3:0] $end
$var reg 4 < A01 [3:0] $end
$var reg 4 = A10 [3:0] $end
$var reg 4 > A11 [3:0] $end
$var reg 4 ? B00 [3:0] $end
$var reg 4 @ B01 [3:0] $end
$var reg 4 A B10 [3:0] $end
$var reg 4 B B11 [3:0] $end
$upscope $end
$scope module norm $end
$var wire 1 - clk $end
$var reg 8 C result00 [7:0] $end
$var reg 8 D result01 [7:0] $end
$var reg 8 E result10 [7:0] $end
$var reg 8 F result11 [7:0] $end
$var reg 2 G state [1:0] $end
$upscope $end
$scope module display $end
$var wire 1 - clk $end
$var wire 8 H val0 [7:0] $end
$var wire 8 I val1 [7:0] $end
$var wire 8 J val2 [7:0] $end
$var wire 8 K val3 [7:0] $end
$var reg 4 L an [3:0] $end
$var reg 7 M seg [6:0] $end
$var reg 2 N refresh_counter [1:0] $end
$var reg 4 O current_value [3:0] $end
$upscope $end
$upscope $end
$upscope $end
$enddefinitions $end

#0
$dumpvars
0!
0"
bx #
b1110 $
bx %
bx &
bx '
bx (
bx )
bx *
bx +
bx ,
0-
0.
bx /
bx 0
bx 1
bx 2
bx 3
bx 4
bx 5
bx 6
bx 7
bx 8
bx 9
bx :
b10 ;
b11 <
b1 =
b100 >
b101 ?
b110 @
b111 A
b1000 B
bx C
bx D
bx E
bx F
b0 G
bx H
bx I
bx J
bx K
b1110 L
bx M
b0 N
bx O
$end

#5000
1!
b11001 #
b1101 $
b11111 %
b100100 &
b100001 '
b100110 (
b11111 )
1-
b11111 /
b100100 0
b100001 1
b100110 2
b11111 3
b11111 7
b100100 8
b100001 9
b100110 :
b11111 C
b1 G
b11111 H
b100100 I
b100001 J
b100110 K
b1101 L
b11001 M
b1 N
b100 O

#10000
0!
0-

#15000
1!
b1111001 #
b1011 $
b100100 *
1-
b100100 4
b100100 D
b10 G
b1011 L
b1111001 M
b10 N
b1 O

#20000
0!
0-

#25000
1!
b10 #
b111 $
b100001 +
1-
b100001 5
b100001 E
b11 G
b111 L
b10 M
b11 N
b110 O

#30000
0!
0-

#35000
1!
b1110 #
b1110 $
b100110 ,
1-
b100110 6
b100110 F
b0 G
b1110 L
b1110 M
b0 N
b1111 O

#40000
0!
0-

#45000
1!
b11001 #
b1101 $
1-
b1 G
b1101 L
b11001 M
b1 N
b100 O

#50000
0!
0-

#55000
1!
b1111001 #
b1011 $
1-
b10 G
b1011 L
b1111001 M
b10 N
b1 O

#60000
0!
0-

#65000
1!
b10 #
b111 $
1-
b11 G
b111 L
b10 M
b11 N
b110 O

#70000
0!
0-

#75000
1!
b1110 #
b1110 $
1-
b0 G
b1110 L
b1110 M
b0 N
b1111 O

#80000
0!
0-

#85000
1!
b11001 #
b1101 $
1-
b1 G
b1101 L
b11001 M
b1 N
b100 O

#90000
0!
0-

#95000
1!
b1111001 #
b1011 $
1-
b10 G
b1011 L
b1111001 M
b10 N
b1 O

#100000
0!
1"
0-
1.

#105000
1!
b10 #
b111 $
1-
b11 G
b111 L
b10 M
b11 N
b110 O

#110000
0!
0-

#115000
1!
b1110 #
b1110 $
1-
b0 G
b1110 L
b1110 M
b0 N
b1111 O

#120000
0!
0-

#125000
1!
b11001 #
b1101 $
1-
b1 G
b1101 L
b11001 M
b1 N
b100 O

#130000
0!
0-

#135000
1!
b1111001 #
b1011 $
1-
b10 G
b1011 L
b1111001 M
b10 N
b1 O

#140000
0!
0-

#145000
1!
b10 #
b111 $
1-
b11 G
b111 L
b10 M
b11 N
b110 O

#150000
0!
0-

#155000
1!
b1110 #
b1110 $
1-
b0 G
b1110 L
b1110 M
b0 N
b1111 O

#160000
0!
0-

#165000
1!
b11001 #
b1101 $
1-
b1 G
b1101 L
b11001 M
b1 N
b100 O

#170000
0!
0-

#175000
1!
b1111001 #
b1011 $
1-
b10 G
b1011 L
b1111001 M
b10 N
b1 O

#180000
0!
0-

#185000
1!
b10 #
b111 $
1-
b11 G
b111 L
b10 M
b11 N
b110 O

